ankisync/__init__.py
ankisync/anki.py
ankisync/anki_db.py
ankisync/anki_util.py
ankisync/ankiconnect.py
ankisync/apkg.py
ankisync/builder/__init__.py
ankisync/builder/decks.py
ankisync/builder/default.py
ankisync/builder/guid.py
ankisync/builder/models.py
ankisync/builder/notes.py
ankisync/dir.py
ankisync/presets/__init__.py
ankisync/presets/default.json
ankisync/presets/wanki_min.json
ankisync/util.py
ankisync-0.2.3.1.dist-info/LICENSE
ankisync-0.2.3.1.dist-info/WHEEL
ankisync-0.2.3.1.dist-info/METADATA
ankisync-0.2.3.1.dist-info/RECORD
