Metadata-Version: 2.1
Name: ankisync
Version: 0.2.3.1
Summary: Doing in Anki what AnkiConnect cannot do
Home-page: https://github.com/patarapolw/ankisync
License: MIT
Keywords: anki-flashcards
Author: Pacharapol Withayasakpunt
Author-email: patarapolw@gmail.com
Requires-Python: >=3.7
Classifier: Development Status :: 7 - Inactive
Classifier: License :: OSI Approved :: MIT License
Classifier: Programming Language :: Python :: 3
Classifier: Programming Language :: Python :: 3.7
Classifier: Programming Language :: Python :: 3.8
Classifier: Programming Language :: Python :: 3.9
Requires-Dist: appdirs (>=1.4,<2.0)
Requires-Dist: peewee (>=3.7,<4.0)
Requires-Dist: psutil (>=5.4,<6.0)
Requires-Dist: tinydb (>=3.11,<4.0)
Project-URL: Repository, https://github.com/patarapolw/ankisync
